{
  "blog" : {
    "User" : [ {
      "name" : "john@abstratt.com"
    }, {
      "name" : "mary@abstratt.com"
    } ],
    "Article" : [ {
      "title" : "John's post",
      "body" : "Just a guest post",
      "createdAt" : "2015/09/13",
      "user" : "User@1"
    }, {
      "title" : "Mary's post",
      "body" : "This is John's post.",
      "createdAt" : "2015/09/13",
      "user" : "User@2"
    } ],
    "Comment" : [ {
      "body" : "c1",
      "createdAt" : "2015/09/13",
      "article" : "Article@2",
      "user" : "User@1"
    }, {
      "body" : "c2",
      "createdAt" : "2015/09/13",
      "article" : "Article@2",
      "user" : "User@1"
    } ]
  }
}